data/ca_template.xlsx
data/cp_template.xlsx
euroncap_rating_2026/__init__.py
euroncap_rating_2026/__main__.py
euroncap_rating_2026/cli.py
euroncap_rating_2026/common.py
euroncap_rating_2026/config.py
euroncap_rating_2026/crash_avoidance/__init__.py
euroncap_rating_2026/crash_avoidance/compute_score.py
euroncap_rating_2026/crash_avoidance/data_model.py
euroncap_rating_2026/crash_avoidance/generate_template.py
euroncap_rating_2026/crash_avoidance/matrix_processing.py
euroncap_rating_2026/crash_avoidance/preprocess.py
euroncap_rating_2026/crash_avoidance/report_writer.py
euroncap_rating_2026/crash_avoidance/robustness_layer.py
euroncap_rating_2026/crash_avoidance/test_info.py
euroncap_rating_2026/crash_protection/__init__.py
euroncap_rating_2026/crash_protection/body_region.py
euroncap_rating_2026/crash_protection/compute_score.py
euroncap_rating_2026/crash_protection/criteria.py
euroncap_rating_2026/crash_protection/data_loader.py
euroncap_rating_2026/crash_protection/dummy.py
euroncap_rating_2026/crash_protection/generate_template.py
euroncap_rating_2026/crash_protection/load_case.py
euroncap_rating_2026/crash_protection/measurement.py
euroncap_rating_2026/crash_protection/preprocess.py
euroncap_rating_2026/crash_protection/report_writer.py
euroncap_rating_2026/crash_protection/seat.py
euroncap_rating_2026/crash_protection/vru_processing.py
euroncap_rating_2026/profiler.py
euroncap_rating_2026/version.py
euroncap_rating_2026-2.0.2.dist-info/LICENSE
euroncap_rating_2026-2.0.2.dist-info/METADATA
euroncap_rating_2026-2.0.2.dist-info/WHEEL
euroncap_rating_2026-2.0.2.dist-info/entry_points.txt
euroncap_rating_2026-2.0.2.dist-info/RECORD
