Metadata-Version: 2.1
Name: euroncap-rating-2026
Version: 2.0.2
Summary: This project implements Euro NCAP Rating Calculator 2026 to compute test scores
License: Apache-2.0
Author: Danilo Romano
Author-email: danilo@ivex.ai
Requires-Python: >=3.10,<4.0
Classifier: License :: OSI Approved :: Apache Software License
Classifier: Programming Language :: Python :: 3
Classifier: Programming Language :: Python :: 3.10
Classifier: Programming Language :: Python :: 3.11
Classifier: Programming Language :: Python :: 3.12
Requires-Dist: click (>=8.1.7,<9.0.0)
Requires-Dist: openpyxl (>=3.1.5,<4.0.0)
Requires-Dist: pandas (>=2.2.3,<3.0.0)
Requires-Dist: pdoc (>=15.0.1,<16.0.0)
Requires-Dist: pydantic (>=2.11.1,<3.0.0)
Requires-Dist: pydantic-settings (>=2.8.1,<3.0.0)
